django_site_tag/__init__.py
django_site_tag/apps.py
django_site_tag/middleware.py
django_site_tag/utils.py
django_site_tag-0.0.1.dist-info/LICENSE
django_site_tag-0.0.1.dist-info/METADATA
django_site_tag-0.0.1.dist-info/WHEEL
django_site_tag-0.0.1.dist-info/top_level.txt
django_site_tag-0.0.1.dist-info/RECORD
