Metadata-Version: 2.1
Name: django-site-tag
Version: 0.0.1
Summary: Tag each page on your website with an indicator text or image
Home-page: https://github.com/yudori/django-site-tag
Author: Richard Oyudo
Author-email: ebube.rc@gmail.com
License: UNKNOWN
Platform: UNKNOWN
Classifier: Programming Language :: Python :: 3
Classifier: License :: OSI Approved :: MIT License
Classifier: Operating System :: OS Independent
